oar/__init__.py
oar/client.py
oar/config.py
oar/consts.py
oar/models.py
oar/plugin.py
oar/report.py
pytest_oar-2.0.3.dist-info/METADATA
pytest_oar-2.0.3.dist-info/WHEEL
pytest_oar-2.0.3.dist-info/RECORD
